dbt_mcp/.gitignore
dbt_mcp/__init__.py
dbt_mcp/main.py
dbt_mcp/py.typed
dbt_mcp/config/config.py
dbt_mcp/config/config_providers.py
dbt_mcp/config/dbt_project.py
dbt_mcp/config/dbt_yaml.py
dbt_mcp/config/headers.py
dbt_mcp/config/settings.py
dbt_mcp/config/transport.py
dbt_mcp/dbt_admin/__init__.py
dbt_mcp/dbt_admin/client.py
dbt_mcp/dbt_admin/constants.py
dbt_mcp/dbt_admin/tools.py
dbt_mcp/dbt_admin/run_artifacts/__init__.py
dbt_mcp/dbt_admin/run_artifacts/config.py
dbt_mcp/dbt_admin/run_artifacts/parser.py
dbt_mcp/dbt_cli/binary_type.py
dbt_mcp/dbt_cli/tools.py
dbt_mcp/dbt_cli/models/lineage_types.py
dbt_mcp/dbt_cli/models/manifest.py
dbt_mcp/dbt_codegen/__init__.py
dbt_mcp/dbt_codegen/tools.py
dbt_mcp/discovery/client.py
dbt_mcp/discovery/tools.py
dbt_mcp/discovery/graphql/__init__.py
dbt_mcp/discovery/graphql/get_exposure_details.gql
dbt_mcp/discovery/graphql/get_full_lineage.gql
dbt_mcp/discovery/graphql/get_macro_details.gql
dbt_mcp/discovery/graphql/get_model_details.gql
dbt_mcp/discovery/graphql/get_packages.gql
dbt_mcp/discovery/graphql/get_seed_details.gql
dbt_mcp/discovery/graphql/get_semantic_model_details.gql
dbt_mcp/discovery/graphql/get_snapshot_details.gql
dbt_mcp/discovery/graphql/get_source_details.gql
dbt_mcp/discovery/graphql/get_test_details.gql
dbt_mcp/errors/__init__.py
dbt_mcp/errors/admin_api.py
dbt_mcp/errors/base.py
dbt_mcp/errors/cli.py
dbt_mcp/errors/common.py
dbt_mcp/errors/discovery.py
dbt_mcp/errors/semantic_layer.py
dbt_mcp/errors/sql.py
dbt_mcp/gql/errors.py
dbt_mcp/lsp/__init__.py
dbt_mcp/lsp/lsp_binary_manager.py
dbt_mcp/lsp/lsp_client.py
dbt_mcp/lsp/lsp_connection.py
dbt_mcp/lsp/tools.py
dbt_mcp/lsp/providers/__init__.py
dbt_mcp/lsp/providers/local_lsp_client_provider.py
dbt_mcp/lsp/providers/local_lsp_connection_provider.py
dbt_mcp/lsp/providers/lsp_client_provider.py
dbt_mcp/lsp/providers/lsp_connection_provider.py
dbt_mcp/mcp/server.py
dbt_mcp/oauth/client_id.py
dbt_mcp/oauth/context_manager.py
dbt_mcp/oauth/dbt_platform.py
dbt_mcp-1.7.0.dist-info/METADATA
dbt_mcp-1.7.0.dist-info/WHEEL
dbt_mcp-1.7.0.dist-info/entry_points.txt
dbt_mcp-1.7.0.dist-info/licenses/LICENSE
dbt_mcp-1.7.0.dist-info/RECORD
