Metadata-Version: 2.4
Name: dbt-mcp
Version: 1.7.0
Summary: A MCP (Model Context Protocol) server for interacting with dbt resources.
Project-URL: Documentation, https://docs.getdbt.com/docs/dbt-ai/about-mcp
Project-URL: Issues, https://github.com/dbt-labs/dbt-mcp/issues
Project-URL: Source, https://github.com/dbt-labs/dbt-mcp
Project-URL: Changelog, https://github.com/dbt-labs/dbt-mcp/blob/main/CHANGELOG.md
Author: dbt Labs
License:                                  Apache License
License-File: LICENSE
Keywords: ai-agent,analytics,data,dbt,llm,mcp,model-context-protocol
Classifier: Development Status :: 5 - Production/Stable
Classifier: Intended Audience :: Developers
Classifier: Intended Audience :: Information Technology
Classifier: Intended Audience :: System Administrators
Classifier: License :: OSI Approved :: Apache Software License
Classifier: Operating System :: OS Independent
Classifier: Programming Language :: Python :: 3
Classifier: Topic :: Scientific/Engineering :: Information Analysis
Classifier: Typing :: Typed
Requires-Python: <3.14,>=3.12
Requires-Dist: authlib==1.6.6
Requires-Dist: dbt-protos==1.0.382
Requires-Dist: dbt-sl-sdk[sync]==0.13.1
Requires-Dist: dbtlabs-vortex==0.2.0
Requires-Dist: fastapi==0.116.1
Requires-Dist: filelock>=3.18.0
Requires-Dist: httpx==0.28.1
Requires-Dist: mcp[cli]==1.23.1
Requires-Dist: pydantic-settings==2.10.1
Requires-Dist: pyjwt==2.10.1
Requires-Dist: pyyaml==6.0.2
Requires-Dist: requests==2.32.4
Requires-Dist: uvicorn>=0.31.1
